luigi/__init__.py
luigi/__main__.py
luigi/batch_notifier.py
luigi/cmdline.py
luigi/cmdline_parser.py
luigi/configuration.py
luigi/date_interval.py
luigi/db_task_history.py
luigi/event.py
luigi/execution_summary.py
luigi/file.py
luigi/format.py
luigi/interface.py
luigi/local_target.py
luigi/lock.py
luigi/mock.py
luigi/notifications.py
luigi/parameter.py
luigi/process.py
luigi/retcodes.py
luigi/rpc.py
luigi/scheduler.py
luigi/server.py
luigi/six.py
luigi/target.py
luigi/task.py
luigi/task_history.py
luigi/task_register.py
luigi/task_status.py
luigi/util.py
luigi/worker.py
luigi/contrib/__init__.py
luigi/contrib/bigquery.py
luigi/contrib/bigquery_avro.py
luigi/contrib/dataproc.py
luigi/contrib/docker_runner.py
luigi/contrib/ecs.py
luigi/contrib/esindex.py
luigi/contrib/external_program.py
luigi/contrib/ftp.py
luigi/contrib/gcp.py
luigi/contrib/gcs.py
luigi/contrib/hadoop.py
luigi/contrib/hadoop_jar.py
luigi/contrib/hive.py
luigi/contrib/kubernetes.py
luigi/contrib/mongodb.py
luigi/contrib/mrrunner.py
luigi/contrib/mssqldb.py
luigi/contrib/mysqldb.py
luigi/contrib/opener.py
luigi/contrib/pig.py
luigi/contrib/postgres.py
luigi/contrib/pyspark_runner.py
luigi/contrib/rdbms.py
luigi/contrib/redis_store.py
luigi/contrib/redshift.py
luigi/contrib/s3.py
luigi/contrib/salesforce.py
luigi/contrib/scalding.py
luigi/contrib/sge.py
luigi/contrib/sge_runner.py
luigi/contrib/simulate.py
luigi/contrib/spark.py
luigi/contrib/sparkey.py
luigi/contrib/sqla.py
luigi/contrib/ssh.py
luigi/contrib/target.py
luigi/contrib/webhdfs.py
luigi/contrib/hdfs/__init__.py
luigi/contrib/hdfs/abstract_client.py
luigi/contrib/hdfs/clients.py
luigi/contrib/hdfs/config.py
luigi/contrib/hdfs/error.py
luigi/contrib/hdfs/format.py
luigi/contrib/hdfs/hadoopcli_clients.py
luigi/contrib/hdfs/snakebite_client.py
luigi/contrib/hdfs/target.py
luigi/contrib/hdfs/webhdfs_client.py
luigi/static/visualiser/index.html
luigi-2.7.2.dist-info/DESCRIPTION.rst
luigi-2.7.2.dist-info/METADATA
luigi-2.7.2.dist-info/RECORD
luigi-2.7.2.dist-info/WHEEL
luigi-2.7.2.dist-info/entry_points.txt
luigi-2.7.2.dist-info/metadata.json
luigi-2.7.2.dist-info/top_level.txt
