Metadata-Version: 2.0
Name: luigi
Version: 2.7.2
Summary: Workflow mgmgt + task scheduling + dependency resolution
Home-page: https://github.com/spotify/luigi
Author: The Luigi Authors
Author-email: UNKNOWN
License: Apache License 2.0
Platform: UNKNOWN
Classifier: Development Status :: 5 - Production/Stable
Classifier: Environment :: Console
Classifier: Environment :: Web Environment
Classifier: Intended Audience :: Developers
Classifier: Intended Audience :: System Administrators
Classifier: License :: OSI Approved :: Apache Software License
Classifier: Programming Language :: Python :: 2.7
Classifier: Programming Language :: Python :: 3.3
Classifier: Programming Language :: Python :: 3.4
Classifier: Programming Language :: Python :: 3.5
Classifier: Topic :: System :: Monitoring
Requires-Dist: python-daemon (<3.0)
Requires-Dist: tornado (>=4.0,<5)
